tocm_reference_data/__init__.py
tocm_reference_data/base_class.py
tocm_reference_data/utilities.py
tocm_reference_data-0.1.dist-info/LICENSE
tocm_reference_data-0.1.dist-info/METADATA
tocm_reference_data-0.1.dist-info/WHEEL
tocm_reference_data-0.1.dist-info/top_level.txt
tocm_reference_data-0.1.dist-info/RECORD
