Metadata-Version: 2.1
Name: tocm-reference-data
Version: 0.1
Summary: Reference data used in my research
Home-page: https://github.com/marickmanrho/tocm_reference_data
Author: Marick Manrho
Author-email: marickmanrho@gmail.com
License: MIT
Keywords: scientific,University of Groningen
Platform: any
Classifier: Programming Language :: Python :: 3
Classifier: Natural Language :: English
Classifier: Operating System :: OS Independent
Classifier: Intended Audience :: Science/Research
Classifier: Topic :: Scientific/Engineering
Classifier: Topic :: Scientific/Engineering :: Physics
License-File: LICENSE
Requires-Dist: numpy (>=1.19.5)
Requires-Dist: pandas (>=1.1.5)
Requires-Dist: pkg-resources (>=0.0.0)
Requires-Dist: python-dateutil (>=2.8.1)
Requires-Dist: pytz (>=2021.1)
Requires-Dist: six (>=1.16.0)
